parse_czi/__init__.py
parse_czi/zenlite.py
parse_czi/zenlite_ultrafast.py
parse_czi-0.1.0.dist-info/METADATA
parse_czi-0.1.0.dist-info/WHEEL
parse_czi-0.1.0.dist-info/entry_points.txt
parse_czi-0.1.0.dist-info/top_level.txt
parse_czi-0.1.0.dist-info/RECORD
