Metadata-Version: 2.4
Name: parse-czi
Version: 0.1.0
Summary: Utilities for parsing Zeiss CZI files
Author: LOOLO
License-Expression: MIT
Requires-Python: >=3.8
Requires-Dist: numpy~=1.26.4
Requires-Dist: tifffile~=2023.2.28
Requires-Dist: aicsimageio~=4.14.0
Requires-Dist: czifile~=2019.7.2
